esak/__init__.py
esak/exceptions.py
esak/schemas/__init__.py
esak/schemas/base.py
esak/schemas/character.py
esak/schemas/comic.py
esak/schemas/creator.py
esak/schemas/event.py
esak/schemas/generic.py
esak/schemas/series.py
esak/schemas/story.py
esak/schemas/urls.py
esak/session.py
esak/sqlite_cache.py
esak-2.0.0.dist-info/LICENSE
esak-2.0.0.dist-info/METADATA
esak-2.0.0.dist-info/WHEEL
esak-2.0.0.dist-info/RECORD
