Metadata-Version: 2.1
Name: esak
Version: 2.0.0
Summary: Python wrapper for the Marvel API.
License: MIT
Author: Brian Pepple
Author-email: bdpepple@gmail.com
Maintainer: Brian Pepple
Maintainer-email: bdpepple@gmail.com
Requires-Python: >=3.10,<4.0
Classifier: Framework :: Pydantic :: 2
Classifier: Intended Audience :: Developers
Classifier: License :: OSI Approved :: MIT License
Classifier: Natural Language :: English
Classifier: Operating System :: OS Independent
Classifier: Programming Language :: Python
Classifier: Programming Language :: Python :: 3
Classifier: Programming Language :: Python :: 3.10
Classifier: Programming Language :: Python :: 3.11
Classifier: Programming Language :: Python :: 3.12
Classifier: Programming Language :: Python :: 3.13
Classifier: Topic :: Utilities
Classifier: Typing :: Typed
Requires-Dist: pydantic (>=2.8.0,<3.0.0)
Requires-Dist: requests (>=2.26.0,<3.0.0)
Project-URL: Bug Tracker, https://github.com/Metron-Project/esak/issues
Project-URL: Homepage, https://github.com/Metron-Project/esak
